fletx/__init__.py
fletx/__main__.py
fletx/app.py
fletx/cli/__init__.py
fletx/cli/__pycache__/__init__.cpython-312.pyc
fletx/cli/commands/__init__.py
fletx/cli/commands/base.py
fletx/cli/commands/generate.py
fletx/cli/commands/newproject.py
fletx/cli/commands/runproject.py
fletx/cli/commands/__pycache__/__init__.cpython-312.pyc
fletx/cli/commands/__pycache__/base.cpython-312.pyc
fletx/cli/commands/__pycache__/generate.cpython-312.pyc
fletx/cli/commands/__pycache__/newcomponent.cpython-312.pyc
fletx/cli/commands/__pycache__/newproject.cpython-312.pyc
fletx/cli/commands/__pycache__/runproject.cpython-312.pyc
fletx/cli/templates/__init__.py
fletx/cli/templates/__pycache__/__init__.cpython-312.pyc
fletx/cli/templates/component/component.py.tpl
fletx/cli/templates/controller/controller.py.tpl
fletx/cli/templates/page/page.py.tpl
fletx/cli/templates/project/.python-version.tpl
fletx/cli/templates/project/README.md.tpl
fletx/cli/templates/project/main.py.tpl
fletx/cli/templates/project/pyproject.toml.tpl
fletx/cli/templates/project/requirements.txt.tpl
fletx/cli/templates/project/app/__init__.py.tpl
fletx/cli/templates/project/app/routes.py.tpl
fletx/cli/templates/project/app/components/__init__.py.tpl
fletx/cli/templates/project/app/components/reactive_text.py
fletx/cli/templates/project/app/controllers/__init__.py.tpl
fletx/cli/templates/project/app/controllers/counter.py
fletx/cli/templates/project/app/models/__ini__.py.tpl
fletx/cli/templates/project/app/pages/__init__.py.tpl
fletx/cli/templates/project/app/pages/counter.py.tpl
fletx/cli/templates/project/app/services/__init__.py.tpl
fletx/cli/templates/project/assets/logo.png
fletx/cli/templates/service/service.py.tpl
fletx/core/__init__.py
fletx/core/controller.py
fletx/core/di.py
fletx/core/effects.py
fletx/core/factory.py
fletx/core/http.py
fletx/core/page.py
fletx/core/route_config.py
fletx/core/router.py
fletx/core/services.py
fletx/core/state.py
fletx/core/types.py
fletx/core/widget.py
fletxr-0.1.3.dist-info/licenses/LICENSE
fletxr-0.1.3.dist-info/METADATA
fletxr-0.1.3.dist-info/WHEEL
fletxr-0.1.3.dist-info/entry_points.txt
fletxr-0.1.3.dist-info/top_level.txt
fletxr-0.1.3.dist-info/RECORD
