Metadata-Version: 2.4
Name: FletXr
Version: 0.1.3
Summary: The GetX-inspired Python Framework for Building Reactive, Cross-Platform Apps with Flet
Home-page: https://github.com/AllDotPy/FletX.git
Author: #Einswilli
Author-email: #Einswilli <einswilligoeh@email.com>
Project-URL: Homepage, https://github.com/AllDotPy/FletX
Requires-Python: >=3.12
License-File: LICENSE
Requires-Dist: aiohttp>=3.12.13
Requires-Dist: build>=1.2.2.post1
Requires-Dist: flet[all]>=0.28.3
Requires-Dist: httpx>=0.28.1
Requires-Dist: logging>=0.4.9.6
Requires-Dist: pydantic>=2.11.5
Requires-Dist: setuptools>=80.8.0
Requires-Dist: uvloop>=0.21.0
Provides-Extra: dev
Requires-Dist: pytest; extra == "dev"
Requires-Dist: black; extra == "dev"
Requires-Dist: mypy; extra == "dev"
Requires-Dist: twine; extra == "dev"
Requires-Dist: uv; extra == "dev"
Requires-Dist: build; extra == "dev"
Dynamic: author
Dynamic: home-page
Dynamic: license-file
